sanitizy
