Metadata-Version: 2.1
Name: sanitizy
Version: 1.1.6
Summary: Helpful module to secure flask apps
Home-page: https://github.com/AlaBouali/sanitizy
Author: AlaBouali
Author-email: trap.leader.123@gmail.com
License: MIT License
Platform: UNKNOWN
Classifier: Programming Language :: Python
Classifier: License :: OSI Approved :: MIT License 
Requires-Python: >=2.7
